{"titre":"Sainte Eulalie de Barcelone","attributs":"Elle est représentée avec une palme et une croix.","texte":"Eulalie de Barcelone ou de Mérida est née en 289 et est morte en 301.\r\nAu cours des persécutions des Chrétiens ordonnées dans tout l'empire romain par l'empereur Dioclétien, Eulalie, une jeune fille de 13 ans appartenant à une riche famille de Mérida, refuse de renier sa foi.\r\nElle est alors persécutée puis condamnée au bûcher.\r\nEulalie fait preuve d'un courage exemplaire. Au moment où elle meurt, on voit une colombe blanche sortir de sa bouche et s'élever dans le ciel.","stpatron":"Elle est le saint patron de Barcelone (ville d'Espagne).","fete":"10 décembre","enfant":"Eulalie"}